georgian_hyphenation/__init__.py
georgian_hyphenation/hyphenator.py
georgian_hyphenation-2.2.6.1.dist-info/licenses/LICENSE.txt
georgian_hyphenation-2.2.6.1.dist-info/METADATA
georgian_hyphenation-2.2.6.1.dist-info/WHEEL
georgian_hyphenation-2.2.6.1.dist-info/top_level.txt
georgian_hyphenation-2.2.6.1.dist-info/RECORD
