Metadata-Version: 2.4
Name: georgian-hyphenation
Version: 2.2.6.1
Summary: Georgian Language Hyphenation Library v2.2.6 - Preserves compound word hyphens
Home-page: https://github.com/guramzhgamadze/georgian-hyphenation
Author: Guram Zhgamadze
Author-email: Guram Zhgamadze <guramzhgamadze@gmail.com>
License: MIT
Project-URL: Homepage, https://github.com/guramzhgamadze/georgian-hyphenation
Project-URL: Repository, https://github.com/guramzhgamadze/georgian-hyphenation
Project-URL: Documentation, https://github.com/guramzhgamadze/georgian-hyphenation#readme
Project-URL: Bug Tracker, https://github.com/guramzhgamadze/georgian-hyphenation/issues
Keywords: georgian,hyphenation,syllabification,nlp,linguistics,kartuli,dictionary
Classifier: Development Status :: 5 - Production/Stable
Classifier: Intended Audience :: Developers
Classifier: License :: OSI Approved :: MIT License
Classifier: Programming Language :: Python :: 3
Classifier: Programming Language :: Python :: 3.7
Classifier: Programming Language :: Python :: 3.8
Classifier: Programming Language :: Python :: 3.9
Classifier: Programming Language :: Python :: 3.10
Classifier: Programming Language :: Python :: 3.11
Classifier: Programming Language :: Python :: 3.12
Classifier: Topic :: Text Processing :: Linguistic
Classifier: Natural Language :: Georgian
Requires-Python: >=3.7
License-File: LICENSE.txt
Provides-Extra: dev
Requires-Dist: pytest>=7.0; extra == "dev"
Dynamic: author
Dynamic: home-page
Dynamic: license-file
Dynamic: requires-python
